louvainvsleiden/__init__.py
louvainvsleiden/calc_mod_list.py
louvainvsleiden/leiden.py
louvainvsleiden/leiden_pure.py
louvainvsleiden/louvain.py
louvainvsleiden/louvain_pure.py
louvainvsleiden-0.1.dist-info/METADATA
louvainvsleiden-0.1.dist-info/WHEEL
louvainvsleiden-0.1.dist-info/top_level.txt
louvainvsleiden-0.1.dist-info/RECORD
