Metadata-Version: 2.1
Name: louvainvsleiden
Version: 0.1
Summary: For sampling the louvain method and leiden method on different networks
Home-page: https://github.com/cannon-complexity/louvainvsleiden
Author: cannon-complexity
Author-email: cannon.complexity@gmail.com
License: MIT
Requires-Dist: leidenalg
Requires-Dist: copy
Requires-Dist: importlib
Requires-Dist: itertools
Requires-Dist: math
Requires-Dist: statistics
Requires-Dist: sigfig
Requires-Dist: time
Requires-Dist: igraph
Requires-Dist: networkx
Requires-Dist: numpy
Requires-Dist: pandas
Requires-Dist: sklearn
Requires-Dist: matplotlib
Requires-Dist: seaborn
Requires-Dist: mplcyberpunk
